robo_gym/__init__.py
robo_gym/envs/__init__.py
robo_gym/envs/simulation_wrapper.py
robo_gym/envs/mir100/__init__.py
robo_gym/envs/mir100/mir100.py
robo_gym/envs/ur10/__init__.py
robo_gym/envs/ur10/ur10.py
robo_gym/utils/__init__.py
robo_gym/utils/kinematics_utils.py
robo_gym/utils/mir100_utils.py
robo_gym/utils/ur_utils.py
robo_gym/utils/utils.py
robo_gym-0.1.1.data/scripts/run-rs-side-standard
robo_gym-0.1.1.dist-info/LICENSE
robo_gym-0.1.1.dist-info/METADATA
robo_gym-0.1.1.dist-info/WHEEL
robo_gym-0.1.1.dist-info/top_level.txt
robo_gym-0.1.1.dist-info/RECORD
